{
    "review_info": {
        "id": "1506574774455-REVIEW",
        "user_name": "",
        "email": "pogo@gmail.com",
        "comment": "Luw zirge agidunub giide pi ko saf hogsulaf ijizac wod ina zu sutmijaci gijano.",
        "rating": -0.4659,
        "property": []
    },
    "entities": [
        {
            "id": "1506574774455-MAIN",
            "base_score": 0.3927,
            "property": [
                {
                    "key": "Size",
                    "value": "5.0 inches (~65.1% screen-to-body ratio)"
                },
                {
                    "key": "OS",
                    "value": "Android 5.0 (Lollipop)"
                },
                {
                    "key": "Video",
                    "value": "1080p@30fps"
                },
                {
                    "key": "Card slot",
                    "value": "microSD, up to 64 GB (dedicated slot)"
                },
                {
                    "key": "Colors",
                    "value": "Charcoal Black, Pearl White, Cherry Red"
                },
                {
                    "key": "Bluetooth",
                    "value": "4.0, A2DP, EDR"
                },
                {
                    "key": "Primary",
                    "value": "8 MP, f/2.0, autofocus, LED flash"
                },
                {
                    "key": "Technology",
                    "value": "GSM / HSPA / LTE"
                },
                {
                    "key": "Weight",
                    "value": "155 g (5.47 oz)"
                },
                {
                    "key": "Features",
                    "value": "Geo-tagging, touch focus, face detection, panorama, HDR"
                },
                {
                    "key": "Alert types",
                    "value": "Vibration; MP3, WAV ringtones"
                },
                {
                    "key": "2G bands",
                    "value": "GSM 850 / 900 / 1800 / 1900 "
                },
                {
                    "key": "GPS",
                    "value": "Yes, with A-GPS, GLONASS"
                },
                {
                    "key": "SAR EU",
                    "value": "0.43 W/kg (head)     "
                },
                {
                    "key": "Resolution",
                    "value": "720 x 1280 pixels (~294 ppi pixel density)"
                },
                {
                    "key": "Messaging",
                    "value": "SMS(threaded view), MMS, Email, Push Email, IM"
                },
                {
                    "key": "GPU",
                    "value": "PowerVR SGX544MP2"
                },
                {
                    "key": "Talk time",
                    "value": "Up to 360 h (3G)"
                },
                {
                    "key": "EDGE",
                    "value": "Yes"
                },
                {
                    "key": "Secondary",
                    "value": "2 MP, f/2.0"
                },
                {
                    "key": "4G bands",
                    "value": "LTE band 1(2100), 2(1900), 3(1800), 4(1700/2100), 5(850), 7(2600), 8(900), 28(700) - Taiwan"
                },
                {
                    "key": "Sensors",
                    "value": "Accelerometer, proximity, compass"
                },
                {
                    "key": "Radio",
                    "value": "FM radio"
                },
                {
                    "key": "Announced",
                    "value": "2015, March"
                },
                {
                    "key": "Protection",
                    "value": "Corning Gorilla Glass 3"
                },
                {
                    "key": "Browser",
                    "value": "HTML5"
                },
                {
                    "key": "3G bands",
                    "value": "HSDPA 850 / 900 / 1900 / 2100 "
                },
                {
                    "key": "Speed",
                    "value": "LTE band 1(2100), 2(1900), 3(1800), 4(1700/2100), 5(850), 7(2600), 8(900), 17(700), 20(800) - Global"
                },
                {
                    "key": "Price",
                    "value": "About 180 EUR"
                },
                {
                    "key": "3.5mm jack",
                    "value": "Yes"
                },
                {
                    "key": "Status",
                    "value": "Available. Released 2015, March"
                },
                {
                    "key": "USB",
                    "value": "microUSB 2.0"
                },
                {
                    "key": "SIM",
                    "value": "Micro-SIM"
                },
                {
                    "key": "CPU",
                    "value": "Dual-core 1.6 GHz"
                },
                {
                    "key": "Type",
                    "value": "IPS LCD capacitive touchscreen, 16M colors"
                },
                {
                    "key": "Java",
                    "value": "No"
                },
                {
                    "key": "Chipset",
                    "value": "Intel Atom Z2560"
                },
                {
                    "key": "Stand-by",
                    "value": "Non-removable Li-Po 2500 mAh battery"
                },
                {
                    "key": "Internal",
                    "value": "16 GB, 2 GB RAM"
                },
                {
                    "key": "Multitouch",
                    "value": "Yes"
                },
                {
                    "key": "Dimensions",
                    "value": "148.1 x 71.5 x 10.9 mm (5.83 x 2.81 x 0.43 in)"
                },
                {
                    "key": "WLAN",
                    "value": "Wi-Fi 802.11 b/g/n, Wi-Fi Direct, hotspot"
                },
                {
                    "key": "Loudspeaker",
                    "value": "Yes"
                },
                {
                    "key": "GPRS",
                    "value": "HSPA 42.2/5.76 Mbps, LTE Cat3 100/50 Mbps"
                }
            ],
            "name": "Asus Zenfone 2 ZE500CL"
        }
    ],
    "relationships": [
        {
            "type": "MainEntity",
            "domain": "1506574774455-REVIEW",
            "range": "1506574774455-MAIN"
        }
    ]
}