{
    "review_info": {
        "id": "1506574774540-REVIEW",
        "user_name": "",
        "email": "dedfo@gmail.com",
        "comment": "Gaman soh epfej remkelgu ne hekoh giverbi vidbugde wi pem jewjuw ulka no panebiaz ha.",
        "rating": -0.9621,
        "property": []
    },
    "entities": [
        {
            "id": "1506574774540-MAIN",
            "base_score": 0.9749,
            "property": [
                {
                    "key": "Technology",
                    "value": "GSM / HSPA"
                },
                {
                    "key": "Radio",
                    "value": "Stereo FM radio, RDS"
                },
                {
                    "key": "EDGE",
                    "value": "Yes"
                },
                {
                    "key": "Primary",
                    "value": "5 MP, autofocus, dual-LED flash"
                },
                {
                    "key": "Speed",
                    "value": "HSPA 7.2/2 Mbps"
                },
                {
                    "key": "Weight",
                    "value": "162 g (5.71 oz)"
                },
                {
                    "key": "Messaging",
                    "value": "SMS (threaded view), MMS, Email, Push Email"
                },
                {
                    "key": "Talk time",
                    "value": "Up to 276 h"
                },
                {
                    "key": "Sensors",
                    "value": "Accelerometer, proximity, compass"
                },
                {
                    "key": "Stand-by",
                    "value": "Removable Li-Ion 1230 mAh battery"
                },
                {
                    "key": "Price",
                    "value": "About 120 EUR"
                },
                {
                    "key": "3.5mm jack",
                    "value": "Yes"
                },
                {
                    "key": "Announced",
                    "value": "2011, March"
                },
                {
                    "key": "Type",
                    "value": "S-LCD capacitive touchscreen, 16M colors"
                },
                {
                    "key": "USB",
                    "value": "microUSB 2.0"
                },
                {
                    "key": "WLAN",
                    "value": "Wi-Fi 802.11 b/g/n"
                },
                {
                    "key": "Loudspeaker",
                    "value": "Yes"
                },
                {
                    "key": "Size",
                    "value": "4.3 inches (~63.4% screen-to-body ratio)"
                },
                {
                    "key": "OS",
                    "value": "Microsoft Windows Phone 7"
                },
                {
                    "key": "Video",
                    "value": "720p"
                },
                {
                    "key": "Card slot",
                    "value": "No"
                },
                {
                    "key": "Colors",
                    "value": "Black"
                },
                {
                    "key": "Bluetooth",
                    "value": "2.1, A2DP"
                },
                {
                    "key": "Features",
                    "value": "Geo-tagging"
                },
                {
                    "key": "Alert types",
                    "value": "Vibration, MP3, WAV ringtones"
                },
                {
                    "key": "2G bands",
                    "value": "GSM 850 / 900 / 1800 / 1900 "
                },
                {
                    "key": "GPS",
                    "value": "Yes, with A-GPS; Bing Maps"
                },
                {
                    "key": "Resolution",
                    "value": "480 x 800 pixels (~217 ppi pixel density)"
                },
                {
                    "key": "Chipset",
                    "value": "Qualcomm QSD8250 Snapdragon S1"
                },
                {
                    "key": "Secondary",
                    "value": "No"
                },
                {
                    "key": "Browser",
                    "value": "WAP 2.0/xHTML, HTML"
                },
                {
                    "key": "SAR",
                    "value": "0.96 W/kg (head)     "
                },
                {
                    "key": "3G bands",
                    "value": "HSDPA 850 / 1900 "
                },
                {
                    "key": "Status",
                    "value": "Available. Released 2011, June"
                },
                {
                    "key": "SIM",
                    "value": "Mini-SIM"
                },
                {
                    "key": "CPU",
                    "value": "1.0 GHz Scorpion"
                },
                {
                    "key": "Java",
                    "value": "Yes, MIDP 2.0"
                },
                {
                    "key": "GPU",
                    "value": "Adreno 200"
                },
                {
                    "key": "Internal",
                    "value": "16 GB, 576 MB RAM, 512 MB ROM"
                },
                {
                    "key": "Dimensions",
                    "value": "122 x 68 x 11.2 mm (4.80 x 2.68 x 0.44 in)"
                },
                {
                    "key": "GPRS",
                    "value": "Yes"
                }
            ],
            "name": "HTC HD7S"
        }
    ],
    "relationships": [
        {
            "type": "MainEntity",
            "domain": "1506574774540-REVIEW",
            "range": "1506574774540-MAIN"
        }
    ]
}