{
    "review_info": {
        "id": "1506574774710-REVIEW",
        "user_name": "",
        "email": "romza@gmail.com",
        "comment": "Riup setzud dehaga gepo pa dikzappi fitahwe ebfugzi tagni ef infug dacu rinope keh duccu tetu sakego.",
        "rating": -0.8502,
        "property": []
    },
    "entities": [
        {
            "id": "1506574774710-MAIN",
            "base_score": 0.8583,
            "property": [
                {
                    "key": "Secondary",
                    "value": "No"
                },
                {
                    "key": "Price",
                    "value": "About 40 EUR"
                },
                {
                    "key": "Technology",
                    "value": "GSM"
                },
                {
                    "key": "Size",
                    "value": "2.0 inches (~24.4% screen-to-body ratio)"
                },
                {
                    "key": "Radio",
                    "value": "Stereo FM radio, RDS; scheduled recording"
                },
                {
                    "key": "SIM",
                    "value": "Mini-SIM"
                },
                {
                    "key": "Video",
                    "value": "Yes"
                },
                {
                    "key": "Card slot",
                    "value": "microSD, up to 2 GB (dedicated slot)"
                },
                {
                    "key": "Java",
                    "value": "Yes, MIDP 2.0"
                },
                {
                    "key": "Browser",
                    "value": "WAP 2.0/xHTML"
                },
                {
                    "key": "Bluetooth",
                    "value": "2.1, A2DP"
                },
                {
                    "key": "Stand-by",
                    "value": "Removable Li-Ion 1000 mAh battery"
                },
                {
                    "key": "Primary",
                    "value": "VGA"
                },
                {
                    "key": "Call records",
                    "value": "Yes"
                },
                {
                    "key": "Resolution",
                    "value": "120 x 160 pixels (~100 ppi pixel density)"
                },
                {
                    "key": "Weight",
                    "value": "88.3 g (3.10 oz)"
                },
                {
                    "key": "Alert types",
                    "value": "Vibration; Downloadable polyphonic, MP3 ringtones"
                },
                {
                    "key": "2G bands",
                    "value": "GSM 900 / 1800 / 1900 "
                },
                {
                    "key": "Status",
                    "value": "Discontinued"
                },
                {
                    "key": "GPS",
                    "value": "No"
                },
                {
                    "key": "Announced",
                    "value": "2009, August. Released 2009, September"
                },
                {
                    "key": "Type",
                    "value": "TFT, 65K colors"
                },
                {
                    "key": "Messaging",
                    "value": "SMS, EMS, MMS"
                },
                {
                    "key": "USB",
                    "value": "1.1"
                },
                {
                    "key": "Games",
                    "value": "Yes"
                },
                {
                    "key": "Internal",
                    "value": "12 MB"
                },
                {
                    "key": "Phonebook",
                    "value": "1000 entries, Photo call"
                },
                {
                    "key": "Talk time",
                    "value": "Up to 450 h"
                },
                {
                    "key": "EDGE",
                    "value": "No"
                },
                {
                    "key": "Colors",
                    "value": "Black, Gray, Pink"
                },
                {
                    "key": "3.5mm jack",
                    "value": "No"
                },
                {
                    "key": "Dimensions",
                    "value": "108 x 47 x 12.7 mm (4.25 x 1.85 x 0.5 in)"
                },
                {
                    "key": "WLAN",
                    "value": "No"
                },
                {
                    "key": "Loudspeaker",
                    "value": "Yes"
                },
                {
                    "key": "GPRS",
                    "value": "Yes"
                }
            ],
            "name": "LG GB270"
        }
    ],
    "relationships": [
        {
            "type": "MainEntity",
            "domain": "1506574774710-REVIEW",
            "range": "1506574774710-MAIN"
        }
    ]
}