{
    "review_info": {
        "id": "1506574774740-REVIEW",
        "user_name": "",
        "email": "edosat@gmail.com",
        "comment": "Vihihad af lo te dekorme odeuki afnokga ihnofofi silgaz covdeit lab dinbidaw mov zadwushu.",
        "rating": -0.3565,
        "property": []
    },
    "entities": [
        {
            "id": "1506574774740-MAIN",
            "base_score": 0.5338,
            "property": [
                {
                    "key": "Secondary",
                    "value": "No"
                },
                {
                    "key": "Price",
                    "value": "About 50 EUR"
                },
                {
                    "key": "Technology",
                    "value": "GSM"
                },
                {
                    "key": "Size",
                    "value": "2.0 inches (~24.8% screen-to-body ratio)"
                },
                {
                    "key": "Radio",
                    "value": "Stereo FM radio, RDS, recording"
                },
                {
                    "key": "SIM",
                    "value": "Mini-SIM"
                },
                {
                    "key": "Video",
                    "value": "Yes"
                },
                {
                    "key": "Card slot",
                    "value": "microSD, up to 4 GB (dedicated slot), 2 GB included"
                },
                {
                    "key": "Java",
                    "value": "Yes, MIDP 2.0"
                },
                {
                    "key": "Music play",
                    "value": "Up to 3 h"
                },
                {
                    "key": "Browser",
                    "value": "WAP 2.0/xHTML"
                },
                {
                    "key": "Bluetooth",
                    "value": "2.0, A2DP"
                },
                {
                    "key": "Stand-by",
                    "value": "Removable Li-Po 800 mAh battery"
                },
                {
                    "key": "Primary",
                    "value": "2 MP"
                },
                {
                    "key": "Call records",
                    "value": "40 dialed, 40 received, 40 missed calls"
                },
                {
                    "key": "Resolution",
                    "value": "240 x 320 pixels (~200 ppi pixel density)"
                },
                {
                    "key": "Weight",
                    "value": "100 g (3.53 oz)"
                },
                {
                    "key": "Alert types",
                    "value": "Vibration, MP3 ringtones"
                },
                {
                    "key": "2G bands",
                    "value": "GSM 850 / 900 / 1800 / 1900 "
                },
                {
                    "key": "Status",
                    "value": "Discontinued"
                },
                {
                    "key": "GPS",
                    "value": "No"
                },
                {
                    "key": "Announced",
                    "value": "2009, April. Released 2009, July"
                },
                {
                    "key": "Type",
                    "value": "TFT, 256K colors"
                },
                {
                    "key": "Messaging",
                    "value": "SMS, MMS, Email"
                },
                {
                    "key": "USB",
                    "value": "2.0"
                },
                {
                    "key": "Games",
                    "value": "Yes"
                },
                {
                    "key": "Internal",
                    "value": "50 MB"
                },
                {
                    "key": "Phonebook",
                    "value": "1000 entries, Photocall"
                },
                {
                    "key": "Talk time",
                    "value": "Up to 250 h"
                },
                {
                    "key": "EDGE",
                    "value": "Class 10"
                },
                {
                    "key": "Colors",
                    "value": "Various"
                },
                {
                    "key": "3.5mm jack",
                    "value": "Yes"
                },
                {
                    "key": "Dimensions",
                    "value": "104 x 48 x 15.8 mm (4.09 x 1.89 x 0.62 in)"
                },
                {
                    "key": "WLAN",
                    "value": "No"
                },
                {
                    "key": "Loudspeaker",
                    "value": "Yes"
                },
                {
                    "key": "GPRS",
                    "value": "Class 10"
                }
            ],
            "name": "LG GM210"
        }
    ],
    "relationships": [
        {
            "type": "MainEntity",
            "domain": "1506574774740-REVIEW",
            "range": "1506574774740-MAIN"
        }
    ]
}