{
    "review_info": {
        "id": "1506574774517-REVIEW",
        "user_name": "",
        "email": "legluowa@gmail.com",
        "comment": "Awesa muvbupvu bab tif ake ijud novpijoz dim un fomope fefgongog gi vipa.",
        "rating": -0.6651,
        "property": []
    },
    "entities": [
        {
            "id": "1506574774518-MAIN",
            "base_score": 0.0691,
            "property": [
                {
                    "key": "Size",
                    "value": "5.0 inches"
                },
                {
                    "key": "Speed",
                    "value": "LTE band 1(2100), 3(1800), 7(2600), 8(900), 20(800)"
                },
                {
                    "key": "Secondary",
                    "value": "2 MP, 1080p@30fps"
                },
                {
                    "key": "Sensors",
                    "value": "Accelerometer, gyro, proximity, compass, barometer"
                },
                {
                    "key": "Radio",
                    "value": "Stereo FM radio, RDS"
                },
                {
                    "key": "Announced",
                    "value": "Not announced yet"
                },
                {
                    "key": "Video",
                    "value": "2160p@30fps, 4x lossless digital zoom"
                },
                {
                    "key": "EDGE",
                    "value": "HSPA 42.2/5.76 Mbps, LTE Cat4 150/50 Mbps"
                },
                {
                    "key": "Java",
                    "value": "No"
                },
                {
                    "key": "Browser",
                    "value": "HTML5"
                },
                {
                    "key": "Bluetooth",
                    "value": "4.0, A2DP, EDR, LE, aptX"
                },
                {
                    "key": "3G bands",
                    "value": "HSDPA 850 / 900 / 1900 / 2100 "
                },
                {
                    "key": "Primary",
                    "value": "50 MP (8), Carl Zeiss optics, OIS, auto/manual focus, dual-LED flash"
                },
                {
                    "key": "Loudspeaker",
                    "value": "Yes"
                },
                {
                    "key": "Resolution",
                    "value": "1080 x 1920 pixels (~441 ppi pixel density)"
                },
                {
                    "key": "Weight",
                    "value": "-"
                },
                {
                    "key": "Features",
                    "value": "1/1.2\" sensor size, PureView technology, geo-tagging, face detection, panorama, HDR"
                },
                {
                    "key": "Alert types",
                    "value": "Vibration; MP3, WAV ringtones"
                },
                {
                    "key": "2G bands",
                    "value": "GSM 850 / 900 / 1800 / 1900 - all versions"
                },
                {
                    "key": "Status",
                    "value": "Cancelled"
                },
                {
                    "key": "4G bands",
                    "value": "HSDPA 850 / 900 / 1700 / 1900 / 2100 "
                },
                {
                    "key": "SIM",
                    "value": "Micro-SIM"
                },
                {
                    "key": "CPU",
                    "value": "Quad-core"
                },
                {
                    "key": "Type",
                    "value": "AMOLED capacitive touchscreen, 16M colors"
                },
                {
                    "key": "Protection",
                    "value": "Corning Gorilla Glass 4"
                },
                {
                    "key": "WLAN",
                    "value": "Wi-Fi 802.11 a/b/g/n, dual-band, DLNA, hotspot"
                },
                {
                    "key": "USB",
                    "value": "microUSB 2.0"
                },
                {
                    "key": "Messaging",
                    "value": "SMS (threaded view), MMS, Email, Push Email, IM"
                },
                {
                    "key": "Technology",
                    "value": "GSM / HSPA / LTE"
                },
                {
                    "key": "Internal",
                    "value": "32 GB, 2 GB RAM"
                },
                {
                    "key": "Multitouch",
                    "value": "Yes"
                },
                {
                    "key": "Colors",
                    "value": "Various"
                },
                {
                    "key": "Card slot",
                    "value": "microSD, up to 256 GB (dedicated slot)"
                },
                {
                    "key": "GPS",
                    "value": "Yes, with A-GPS, GLONASS"
                },
                {
                    "key": "3.5mm jack",
                    "value": "Yes"
                },
                {
                    "key": "Dimensions",
                    "value": "-"
                },
                {
                    "key": "NFC",
                    "value": "Yes"
                },
                {
                    "key": "OS",
                    "value": "Microsoft Windows 10"
                },
                {
                    "key": "GPRS",
                    "value": "LTE band 2(1900), 4(1700/2100), 5(850), 17(700)"
                }
            ],
            "name": "Microsoft Lumia 1030"
        }
    ],
    "relationships": [
        {
            "type": "MainEntity",
            "domain": "1506574774517-REVIEW",
            "range": "1506574774518-MAIN"
        }
    ]
}