{
    "review_info": {
        "id": "1506574774360-REVIEW",
        "user_name": "",
        "email": "jikwadpor@gmail.com",
        "comment": "Ji sejocev vigkihlej fedo nos gewibla orajoj cinpivu hidgaslow bohurjir unaule woputep van jevwu hubon ecedemen opoamju.",
        "rating": 0.8183,
        "property": []
    },
    "entities": [
        {
            "id": "1506574774360-MAIN",
            "base_score": 0.8939,
            "property": [
                {
                    "key": "Size",
                    "value": "4.3 inches (~59.8% screen-to-body ratio)"
                },
                {
                    "key": "OS",
                    "value": "Android 4.4.4 (KitKat)"
                },
                {
                    "key": "Secondary",
                    "value": "2 MP"
                },
                {
                    "key": "Video",
                    "value": "720p@30fps"
                },
                {
                    "key": "Card slot",
                    "value": "microSD, up to 256 GB (dedicated slot)"
                },
                {
                    "key": "Colors",
                    "value": "White, Black, Blue"
                },
                {
                    "key": "Bluetooth",
                    "value": "4.0, A2DP"
                },
                {
                    "key": "Primary",
                    "value": "5 MP, f/2.2, 31mm, autofocus, LED flash"
                },
                {
                    "key": "Technology",
                    "value": "GSM / HSPA / LTE"
                },
                {
                    "key": "Weight",
                    "value": "131 g (4.62 oz)"
                },
                {
                    "key": "Features",
                    "value": "Geo-tagging, touch focus, face detection, panorama"
                },
                {
                    "key": "Alert types",
                    "value": "Vibration; MP3, WAV ringtones"
                },
                {
                    "key": "2G bands",
                    "value": "GSM 850 / 900 / 1800 / 1900 - SIM 1 & SIM 2 (dual-SIM model only)"
                },
                {
                    "key": "GPS",
                    "value": "Yes, with A-GPS, GLONASS"
                },
                {
                    "key": "SAR EU",
                    "value": "0.69 W/kg (head)     0.53 W/kg (body)     "
                },
                {
                    "key": "Resolution",
                    "value": "480 x 800 pixels (~217 ppi pixel density)"
                },
                {
                    "key": "Messaging",
                    "value": "SMS(threaded view), MMS, Email, Push Mail, IM"
                },
                {
                    "key": "SAR",
                    "value": "1.57 W/kg (head)     1.22 W/kg (body)     "
                },
                {
                    "key": "GPU",
                    "value": "Mali-400MP2"
                },
                {
                    "key": "Talk time",
                    "value": "Removable Li-Ion 1900 mAh battery"
                },
                {
                    "key": "Music play",
                    "value": "Up to 10 h (3G)"
                },
                {
                    "key": "4G bands",
                    "value": "HSDPA 850 / 900 / 1700(AWS) / 1900 / 2100 - J110M"
                },
                {
                    "key": "Sensors",
                    "value": "Accelerometer, proximity"
                },
                {
                    "key": "Radio",
                    "value": "FM radio, RDS, recording"
                },
                {
                    "key": "Announced",
                    "value": "2015, September"
                },
                {
                    "key": "EDGE",
                    "value": "LTE band 1(2100), 3(1800), 5(850), 7(2600), 8(900), 20(800) - J110F"
                },
                {
                    "key": "Browser",
                    "value": "HTML"
                },
                {
                    "key": "3G bands",
                    "value": "HSDPA 850 / 900 / 2100 - J111F"
                },
                {
                    "key": "Speed",
                    "value": "HSDPA 850 / 900 / 2100 - J110F"
                },
                {
                    "key": "Price",
                    "value": "About 140 EUR"
                },
                {
                    "key": "3.5mm jack",
                    "value": "Yes"
                },
                {
                    "key": "Status",
                    "value": "Available. Released 2015, October"
                },
                {
                    "key": "USB",
                    "value": "microUSB 2.0"
                },
                {
                    "key": "SIM",
                    "value": "Single SIM (Micro-SIM) or Dual SIM (Micro-SIM, dual stand-by)"
                },
                {
                    "key": "CPU",
                    "value": "Quad-core 1.5 GHz Cortex-A7 - J111F"
                },
                {
                    "key": "Type",
                    "value": "Super AMOLED capacitive touchscreen, 16M colors"
                },
                {
                    "key": "Java",
                    "value": "No"
                },
                {
                    "key": "Chipset",
                    "value": "Spreadtrum SC9830"
                },
                {
                    "key": "Internal",
                    "value": "4 GB, 512 MB RAM - J110L"
                },
                {
                    "key": "Multitouch",
                    "value": "Yes"
                },
                {
                    "key": "Dimensions",
                    "value": "130.1 x 67.6 x 9.5 mm (5.12 x 2.66 x 0.37 in)"
                },
                {
                    "key": "WLAN",
                    "value": "Wi-Fi 802.11 b/g/n, Wi-Fi Direct, hotspot"
                },
                {
                    "key": "Loudspeaker",
                    "value": "Yes"
                },
                {
                    "key": "GPRS",
                    "value": "HSDPA 850 / 1900 / 2100 - J110L"
                }
            ],
            "name": "Samsung Galaxy J1 Ace"
        }
    ],
    "relationships": [
        {
            "type": "MainEntity",
            "domain": "1506574774360-REVIEW",
            "range": "1506574774360-MAIN"
        }
    ]
}