{
    "review_info": {
        "id": "1506574774329-REVIEW",
        "user_name": "",
        "email": "otiel@gmail.com",
        "comment": "Tinpug jiwpakle iwe foop bu eha locoud unelazaj ja biltu colsulura me.",
        "rating": -0.0492,
        "property": []
    },
    "entities": [
        {
            "id": "1506574774330-MAIN",
            "base_score": 0.3329,
            "property": [
                {
                    "key": "Size",
                    "value": "5.0 inches (~69.0% screen-to-body ratio)"
                },
                {
                    "key": "OS",
                    "value": "Android 6.0.1 (Marshmallow)"
                },
                {
                    "key": "Features",
                    "value": "Geo-tagging, touch focus, face/smile detection, HDR, panorama"
                },
                {
                    "key": "Video",
                    "value": "1080p@30fps, "
                },
                {
                    "key": "Card slot",
                    "value": "microSD, up to 256 GB (uses SIM 2 slot)"
                },
                {
                    "key": "Colors",
                    "value": "Gold, Rose Gold, Dark Gray"
                },
                {
                    "key": "Bluetooth",
                    "value": "4.1, A2DP, LE"
                },
                {
                    "key": "Primary",
                    "value": "13 MP, f/2.2, autofocus, LED flash, "
                },
                {
                    "key": "Technology",
                    "value": "GSM / HSPA / LTE"
                },
                {
                    "key": "Weight",
                    "value": "131.5 g (4.66 oz)"
                },
                {
                    "key": "Infrared port",
                    "value": "Yes"
                },
                {
                    "key": "Alert types",
                    "value": "Vibration; MP3, WAV ringtones"
                },
                {
                    "key": "2G bands",
                    "value": "GSM 850 / 900 / 1800 / 1900 - SIM 1 & SIM 2"
                },
                {
                    "key": "GPS",
                    "value": "Yes, with A-GPS, GLONASS, BDS"
                },
                {
                    "key": "Resolution",
                    "value": "720 x 1280 pixels (~296 ppi pixel density)"
                },
                {
                    "key": "Messaging",
                    "value": "SMS(threaded view), MMS, Email, Push Mail, IM"
                },
                {
                    "key": "GPU",
                    "value": "Adreno 308"
                },
                {
                    "key": "Secondary",
                    "value": "5 MP, f/2.2"
                },
                {
                    "key": "4G bands",
                    "value": "LTE band 1(2100), 3(1800), 4(1700/2100), 5(850), 7(2600), 20(800), 38(2600), 40(2300)"
                },
                {
                    "key": "Sensors",
                    "value": "Accelerometer, gyro, proximity"
                },
                {
                    "key": "Radio",
                    "value": "FM radio"
                },
                {
                    "key": "Announced",
                    "value": "2016, November"
                },
                {
                    "key": "EDGE",
                    "value": "Yes"
                },
                {
                    "key": "Browser",
                    "value": "HTML5"
                },
                {
                    "key": "3G bands",
                    "value": "HSDPA 850 / 900 / 1900 / 2100 "
                },
                {
                    "key": "Speed",
                    "value": "HSPA, LTE"
                },
                {
                    "key": "Price",
                    "value": "About 110 EUR"
                },
                {
                    "key": "3.5mm jack",
                    "value": "Yes"
                },
                {
                    "key": "Status",
                    "value": "Available. Released 2016, November"
                },
                {
                    "key": "USB",
                    "value": "microUSB 2.0"
                },
                {
                    "key": "SIM",
                    "value": "Hybrid Dual SIM (Nano-SIM/ Micro-SIM, dual stand-by)"
                },
                {
                    "key": "CPU",
                    "value": "Quad-core 1.4 GHz Cortex-A53"
                },
                {
                    "key": "Type",
                    "value": "IPS LCD capacitive touchscreen, 16M colors"
                },
                {
                    "key": "Java",
                    "value": "No"
                },
                {
                    "key": "Chipset",
                    "value": "Qualcomm MSM8917 Snapdragon 425"
                },
                {
                    "key": "Internal",
                    "value": "16/32 GB, 2 GB RAM"
                },
                {
                    "key": "Multitouch",
                    "value": "Yes"
                },
                {
                    "key": "Dimensions",
                    "value": "139.9 x 70.4 x 8.5 mm (5.51 x 2.77 x 0.33 in)"
                },
                {
                    "key": "WLAN",
                    "value": "Wi-Fi 802.11 b/g/n, Wi-Fi Direct, hotspot"
                },
                {
                    "key": "Loudspeaker",
                    "value": "Yes"
                },
                {
                    "key": "GPRS",
                    "value": "Yes"
                }
            ],
            "name": "Xiaomi Redmi 4a"
        },
        {
            "id": "1001574781348255SECONDARY-COMP",
            "name": "Samsung Galaxy S6",
            "base_score": 0.5894,
            "property": []
        },
        {
            "id": "1001527003660357-PRIMARY-F-B",
            "name": "Built-in FM radio",
            "base_score": 0.5695,
            "property": []
        },
        {
            "id": "1001587288369054-SECONDARY-F-B",
            "name": "Built-in FM radio",
            "base_score": 0.996,
            "property": []
        },
        {
            "id": "101511210237142-PRIMARY-F-W",
            "name": "Much more internal storage",
            "base_score": 0.6209,
            "property": []
        },
        {
            "id": "1001588255347639-SECONDARY-F-W",
            "name": "Much more internal storage",
            "base_score": 0.6164,
            "property": []
        },
        {
            "id": "1001551843392478-PRIMARY-F-W",
            "name": "Much higher resolution screen",
            "base_score": 0.5556,
            "property": []
        },
        {
            "id": "1001580927145762-SECONDARY-F-W",
            "name": "Much higher resolution screen",
            "base_score": 0.6878,
            "property": []
        },
        {
            "id": "1001536060730765-PRIMARY-F-W",
            "name": "Much higher PPI screen",
            "base_score": 0.6078,
            "property": []
        },
        {
            "id": "1001599805269579-SECONDARY-F-W",
            "name": "Much higher PPI screen",
            "base_score": 0.9924,
            "property": []
        },
        {
            "id": "1001589962116188-PRIMARY-F-W",
            "name": "Higher resolution movies",
            "base_score": 0.796,
            "property": []
        },
        {
            "id": "1001591888395815-SECONDARY-F-W",
            "name": "Higher resolution movies",
            "base_score": 0.7897,
            "property": []
        },
        {
            "id": "1001552910237435-PRIMARY-F-W",
            "name": "Has an assisted GPS",
            "base_score": 0.7747,
            "property": []
        },
        {
            "id": "1001557342574188-SECONDARY-F-W",
            "name": "Has an assisted GPS",
            "base_score": 0.9609,
            "property": []
        },
        {
            "id": "1001592918667316-PRIMARY-F-W",
            "name": "Significantly faster processor",
            "base_score": 0.9144,
            "property": []
        },
        {
            "id": "1001601705360089-SECONDARY-F-W",
            "name": "Significantly faster processor",
            "base_score": 0.7917,
            "property": []
        },
        {
            "id": "1001532324589255-PRIMARY-F-W",
            "name": "Higher resolution camera",
            "base_score": 0.7342,
            "property": []
        },
        {
            "id": "1001592383393787-SECONDARY-F-W",
            "name": "Higher resolution camera",
            "base_score": 0.7967,
            "property": []
        },
        {
            "id": "1001526947455622-PRIMARY-F-W",
            "name": "Slightly thinner",
            "base_score": 0.5817,
            "property": []
        },
        {
            "id": "1001580035854389-SECONDARY-F-W",
            "name": "Slightly thinner",
            "base_score": 0.5278,
            "property": []
        },
        {
            "id": "1001533638975049-PRIMARY-F-W",
            "name": "Slightly smaller",
            "base_score": 0.6816,
            "property": []
        },
        {
            "id": "1001606277188894-SECONDARY-F-W",
            "name": "Slightly smaller",
            "base_score": 0.9424,
            "property": []
        },
        {
            "id": "1001561567996095SECONDARY-COMP",
            "name": "Motorola Moto E3 Power",
            "base_score": 0.928,
            "property": []
        },
        {
            "id": "1001546289795499-PRIMARY-F-B",
            "name": "Integrated compass",
            "base_score": 0.6614,
            "property": []
        },
        {
            "id": "1001593782684838-SECONDARY-F-B",
            "name": "Integrated compass",
            "base_score": 0.926,
            "property": []
        },
        {
            "id": "1001577933622736-PRIMARY-F-B",
            "name": "Higher resolution camera",
            "base_score": 0.8099,
            "property": []
        },
        {
            "id": "1001555246396621-SECONDARY-F-B",
            "name": "Higher resolution camera",
            "base_score": 0.8174,
            "property": []
        },
        {
            "id": "1001578400534440-PRIMARY-F-B",
            "name": "Faster processor",
            "base_score": 0.8657,
            "property": []
        },
        {
            "id": "1001519316407760-SECONDARY-F-B",
            "name": "Faster processor",
            "base_score": 0.529,
            "property": []
        },
        {
            "id": "1001555300999784-PRIMARY-F-B",
            "name": "Higher resolution movies",
            "base_score": 0.5207,
            "property": []
        },
        {
            "id": "1001593049314830-SECONDARY-F-B",
            "name": "Higher resolution movies",
            "base_score": 0.6368,
            "property": []
        },
        {
            "id": "1001555218634616-PRIMARY-F-B",
            "name": "Lighter",
            "base_score": 0.9426,
            "property": []
        },
        {
            "id": "1001519750688250-SECONDARY-F-B",
            "name": "Lighter",
            "base_score": 0.7923,
            "property": []
        },
        {
            "id": "1001523255446042-PRIMARY-F-B",
            "name": "Slightly smaller",
            "base_score": 0.5416,
            "property": []
        },
        {
            "id": "1001578735487700-SECONDARY-F-B",
            "name": "Slightly smaller",
            "base_score": 0.8374,
            "property": []
        },
        {
            "id": "1001536458264060-PRIMARY-F-B",
            "name": "Slightly thinner",
            "base_score": 0.5431,
            "property": []
        },
        {
            "id": "1001524714473217-SECONDARY-F-B",
            "name": "Slightly thinner",
            "base_score": 0.6015,
            "property": []
        },
        {
            "id": "1001524014455570-PRIMARY-F-W",
            "name": "Much newer bluetooth support",
            "base_score": 0.696,
            "property": []
        },
        {
            "id": "1001560981394422-SECONDARY-F-W",
            "name": "Much newer bluetooth support",
            "base_score": 0.5599,
            "property": []
        },
        {
            "id": "1001557491074504SECONDARY-COMP",
            "name": "Motorola Moto E3 Power",
            "base_score": 0.0123,
            "property": []
        },
        {
            "id": "1001580699194853-PRIMARY-F-B",
            "name": "Integrated compass",
            "base_score": 0.5108,
            "property": []
        },
        {
            "id": "1001596083444196-SECONDARY-F-B",
            "name": "Integrated compass",
            "base_score": 0.9821,
            "property": []
        },
        {
            "id": "1001523637731584-PRIMARY-F-B",
            "name": "Higher resolution camera",
            "base_score": 0.5368,
            "property": []
        },
        {
            "id": "1001546049526848-SECONDARY-F-B",
            "name": "Higher resolution camera",
            "base_score": 0.7825,
            "property": []
        },
        {
            "id": "101514611476312-PRIMARY-F-B",
            "name": "Faster processor",
            "base_score": 0.8095,
            "property": []
        },
        {
            "id": "1001522472525948-SECONDARY-F-B",
            "name": "Faster processor",
            "base_score": 0.8035,
            "property": []
        },
        {
            "id": "1001520432937542-PRIMARY-F-B",
            "name": "Higher resolution movies",
            "base_score": 0.9774,
            "property": []
        },
        {
            "id": "1001605545396267-SECONDARY-F-B",
            "name": "Higher resolution movies",
            "base_score": 0.8036,
            "property": []
        },
        {
            "id": "1001599460652519-PRIMARY-F-B",
            "name": "Lighter",
            "base_score": 0.7653,
            "property": []
        },
        {
            "id": "1001562523286535-SECONDARY-F-B",
            "name": "Lighter",
            "base_score": 0.8798,
            "property": []
        },
        {
            "id": "1001549274360064-PRIMARY-F-B",
            "name": "Slightly smaller",
            "base_score": 0.9822,
            "property": []
        },
        {
            "id": "1001588540332929-SECONDARY-F-B",
            "name": "Slightly smaller",
            "base_score": 0.7626,
            "property": []
        },
        {
            "id": "1001552660575255-PRIMARY-F-B",
            "name": "Slightly thinner",
            "base_score": 0.781,
            "property": []
        },
        {
            "id": "1001536516873354-SECONDARY-F-B",
            "name": "Slightly thinner",
            "base_score": 0.9352,
            "property": []
        },
        {
            "id": "1001585621000735-PRIMARY-F-W",
            "name": "Much newer bluetooth support",
            "base_score": 0.5327,
            "property": []
        },
        {
            "id": "1001526240646677-SECONDARY-F-W",
            "name": "Much newer bluetooth support",
            "base_score": 0.8497,
            "property": []
        },
        {
            "id": "1001529140722869SECONDARY-COMP",
            "name": "Samsung Galaxy S6 edge",
            "base_score": 0.6792,
            "property": []
        },
        {
            "id": "101509713888169-PRIMARY-F-B",
            "name": "Built-in FM radio",
            "base_score": 0.5229,
            "property": []
        },
        {
            "id": "1001597984606635-SECONDARY-F-B",
            "name": "Built-in FM radio",
            "base_score": 0.8764,
            "property": []
        },
        {
            "id": "1001520545707248-PRIMARY-F-W",
            "name": "Much more internal storage",
            "base_score": 0.8069,
            "property": []
        },
        {
            "id": "101515929053841-SECONDARY-F-W",
            "name": "Much more internal storage",
            "base_score": 0.6561,
            "property": []
        },
        {
            "id": "1001538446826513-PRIMARY-F-W",
            "name": "Much higher resolution screen",
            "base_score": 0.5231,
            "property": []
        },
        {
            "id": "1001546759981361-SECONDARY-F-W",
            "name": "Much higher resolution screen",
            "base_score": 0.7059,
            "property": []
        },
        {
            "id": "1001553461717210-PRIMARY-F-W",
            "name": "Much higher PPI screen",
            "base_score": 0.553,
            "property": []
        },
        {
            "id": "1001596316513351-SECONDARY-F-W",
            "name": "Much higher PPI screen",
            "base_score": 0.9017,
            "property": []
        },
        {
            "id": "1001527921388439-PRIMARY-F-W",
            "name": "Higher resolution movies",
            "base_score": 0.5629,
            "property": []
        },
        {
            "id": "1001539299734753-SECONDARY-F-W",
            "name": "Higher resolution movies",
            "base_score": 0.7727,
            "property": []
        },
        {
            "id": "1001542998140097-PRIMARY-F-W",
            "name": "Has an assisted GPS",
            "base_score": 0.5371,
            "property": []
        },
        {
            "id": "101512547987305-SECONDARY-F-W",
            "name": "Has an assisted GPS",
            "base_score": 0.9695,
            "property": []
        },
        {
            "id": "1001580487252448-PRIMARY-F-W",
            "name": "Significantly faster processor",
            "base_score": 0.919,
            "property": []
        },
        {
            "id": "1001574744280709-SECONDARY-F-W",
            "name": "Significantly faster processor",
            "base_score": 0.8487,
            "property": []
        },
        {
            "id": "1001526465727367-PRIMARY-F-W",
            "name": "Higher resolution camera",
            "base_score": 0.7574,
            "property": []
        },
        {
            "id": "1001574439034590-SECONDARY-F-W",
            "name": "Higher resolution camera",
            "base_score": 0.8972,
            "property": []
        },
        {
            "id": "1001523651161326-PRIMARY-F-W",
            "name": "Slightly thinner",
            "base_score": 0.6491,
            "property": []
        },
        {
            "id": "1001546074453906-SECONDARY-F-W",
            "name": "Slightly thinner",
            "base_score": 0.6688,
            "property": []
        },
        {
            "id": "1001598563436141-PRIMARY-F-W",
            "name": "Slightly smaller",
            "base_score": 0.5005,
            "property": []
        },
        {
            "id": "1001547463793705-SECONDARY-F-W",
            "name": "Slightly smaller",
            "base_score": 0.5384,
            "property": []
        },
        {
            "id": "1001528841782316SECONDARY-COMP",
            "name": "Motorola Moto E3",
            "base_score": 0.9723,
            "property": []
        },
        {
            "id": "1001593422606263-PRIMARY-F-B",
            "name": "Integrated compass",
            "base_score": 0.9564,
            "property": []
        },
        {
            "id": "1001538801159665-SECONDARY-F-B",
            "name": "Integrated compass",
            "base_score": 0.7635,
            "property": []
        },
        {
            "id": "1001570897858755-PRIMARY-F-B",
            "name": "Higher resolution camera",
            "base_score": 0.8447,
            "property": []
        },
        {
            "id": "1001581873923938-SECONDARY-F-B",
            "name": "Higher resolution camera",
            "base_score": 0.9753,
            "property": []
        },
        {
            "id": "1001605860927354-PRIMARY-F-B",
            "name": "Faster processor",
            "base_score": 0.6351,
            "property": []
        },
        {
            "id": "1001564622639214-SECONDARY-F-B",
            "name": "Faster processor",
            "base_score": 0.6836,
            "property": []
        },
        {
            "id": "101510901576398-PRIMARY-F-B",
            "name": "Higher resolution movies",
            "base_score": 0.5154,
            "property": []
        },
        {
            "id": "1001598768302265-SECONDARY-F-B",
            "name": "Higher resolution movies",
            "base_score": 0.5164,
            "property": []
        },
        {
            "id": "1001560374860700-PRIMARY-F-B",
            "name": "Lighter",
            "base_score": 0.8448,
            "property": []
        },
        {
            "id": "101514926097450-SECONDARY-F-B",
            "name": "Lighter",
            "base_score": 0.6499,
            "property": []
        },
        {
            "id": "1001524158415502-PRIMARY-F-B",
            "name": "Slightly smaller",
            "base_score": 0.882,
            "property": []
        },
        {
            "id": "1001569659327322-SECONDARY-F-B",
            "name": "Slightly smaller",
            "base_score": 0.9953,
            "property": []
        },
        {
            "id": "1001587742218936-PRIMARY-F-B",
            "name": "Slightly thinner",
            "base_score": 0.8126,
            "property": []
        },
        {
            "id": "1001557888228075-SECONDARY-F-B",
            "name": "Slightly thinner",
            "base_score": 0.6726,
            "property": []
        },
        {
            "id": "1001519359510510-PRIMARY-F-W",
            "name": "Much newer bluetooth support",
            "base_score": 0.7448,
            "property": []
        },
        {
            "id": "1001603904945778-SECONDARY-F-W",
            "name": "Much newer bluetooth support",
            "base_score": 0.924,
            "property": []
        },
        {
            "id": "1001527086380312SECONDARY-COMP",
            "name": "Sony Xperia L1",
            "base_score": 0.7707,
            "property": []
        },
        {
            "id": "1001588774473036-PRIMARY-F-B",
            "name": "Lighter",
            "base_score": 0.7921,
            "property": []
        },
        {
            "id": "1001525483679354-SECONDARY-F-B",
            "name": "Lighter",
            "base_score": 0.8413,
            "property": []
        },
        {
            "id": "1001517235659041-PRIMARY-F-B",
            "name": "Slightly higher PPI screen",
            "base_score": 0.8963,
            "property": []
        },
        {
            "id": "1001586349124324-SECONDARY-F-B",
            "name": "Slightly higher PPI screen",
            "base_score": 0.6829,
            "property": []
        },
        {
            "id": "1001547812924699-PRIMARY-F-B",
            "name": "Slightly smaller",
            "base_score": 0.9456,
            "property": []
        },
        {
            "id": "1001588709825163-SECONDARY-F-B",
            "name": "Slightly smaller",
            "base_score": 0.7562,
            "property": []
        },
        {
            "id": "1001571422615020-PRIMARY-F-W",
            "name": "Larger screen",
            "base_score": 0.7031,
            "property": []
        },
        {
            "id": "1001561163044187-SECONDARY-F-W",
            "name": "Larger screen",
            "base_score": 0.9996,
            "property": []
        },
        {
            "id": "1001529764561007SECONDARY-COMP",
            "name": "HTC Desire 626",
            "base_score": 0.0425,
            "property": []
        },
        {
            "id": "1001533644329898-PRIMARY-F-B",
            "name": "Built-in FM radio",
            "base_score": 0.7861,
            "property": []
        },
        {
            "id": "1001579811505300-SECONDARY-F-B",
            "name": "Built-in FM radio",
            "base_score": 0.6216,
            "property": []
        },
        {
            "id": "101514333070373-PRIMARY-F-B",
            "name": "Higher resolution camera",
            "base_score": 0.6488,
            "property": []
        },
        {
            "id": "1001569369115310-SECONDARY-F-B",
            "name": "Higher resolution camera",
            "base_score": 0.7079,
            "property": []
        },
        {
            "id": "1001521288655630-PRIMARY-F-B",
            "name": "Faster processor",
            "base_score": 0.5218,
            "property": []
        },
        {
            "id": "1001540416688497-SECONDARY-F-B",
            "name": "Faster processor",
            "base_score": 0.6185,
            "property": []
        },
        {
            "id": "101515462077457-PRIMARY-F-B",
            "name": "Higher resolution movies",
            "base_score": 0.6941,
            "property": []
        },
        {
            "id": "101515554831271-SECONDARY-F-B",
            "name": "Higher resolution movies",
            "base_score": 0.7659,
            "property": []
        },
        {
            "id": "1001552741628468-PRIMARY-F-B",
            "name": "Slightly lighter",
            "base_score": 0.6768,
            "property": []
        },
        {
            "id": "1001551769720951-SECONDARY-F-B",
            "name": "Slightly lighter",
            "base_score": 0.724,
            "property": []
        },
        {
            "id": "1001541005418731-PRIMARY-F-W",
            "name": "Has an assisted GPS",
            "base_score": 0.887,
            "property": []
        },
        {
            "id": "1001596224367178-SECONDARY-F-W",
            "name": "Has an assisted GPS",
            "base_score": 0.73,
            "property": []
        }
    ],
    "relationships": [
        {
            "type": "MainEntity",
            "domain": "1506574774329-REVIEW",
            "range": "1506574774330-MAIN"
        },
        {
            "type": "Feature",
            "domain": "1506574774330-MAIN",
            "range": "1001527003660357-PRIMARY-F-B"
        },
        {
            "type": "Feature",
            "domain": "1001574781348255SECONDARY-COMP",
            "range": "1001587288369054-SECONDARY-F-B"
        },
        {
            "type": "BetterThan",
            "domain": "1001527003660357-PRIMARY-F-B",
            "range": "1001587288369054-SECONDARY-F-B"
        },
        {
            "type": "Feature",
            "domain": "1506574774330-MAIN",
            "range": "101511210237142-PRIMARY-F-W"
        },
        {
            "type": "Feature",
            "domain": "1001574781348255SECONDARY-COMP",
            "range": "1001588255347639-SECONDARY-F-W"
        },
        {
            "type": "BetterThan",
            "domain": "1001588255347639-SECONDARY-F-W",
            "range": "101511210237142-PRIMARY-F-W"
        },
        {
            "type": "Feature",
            "domain": "1506574774330-MAIN",
            "range": "1001551843392478-PRIMARY-F-W"
        },
        {
            "type": "Feature",
            "domain": "1001574781348255SECONDARY-COMP",
            "range": "1001580927145762-SECONDARY-F-W"
        },
        {
            "type": "BetterThan",
            "domain": "1001580927145762-SECONDARY-F-W",
            "range": "1001551843392478-PRIMARY-F-W"
        },
        {
            "type": "Feature",
            "domain": "1506574774330-MAIN",
            "range": "1001536060730765-PRIMARY-F-W"
        },
        {
            "type": "Feature",
            "domain": "1001574781348255SECONDARY-COMP",
            "range": "1001599805269579-SECONDARY-F-W"
        },
        {
            "type": "BetterThan",
            "domain": "1001599805269579-SECONDARY-F-W",
            "range": "1001536060730765-PRIMARY-F-W"
        },
        {
            "type": "Feature",
            "domain": "1506574774330-MAIN",
            "range": "1001589962116188-PRIMARY-F-W"
        },
        {
            "type": "Feature",
            "domain": "1001574781348255SECONDARY-COMP",
            "range": "1001591888395815-SECONDARY-F-W"
        },
        {
            "type": "BetterThan",
            "domain": "1001591888395815-SECONDARY-F-W",
            "range": "1001589962116188-PRIMARY-F-W"
        },
        {
            "type": "Feature",
            "domain": "1506574774330-MAIN",
            "range": "1001552910237435-PRIMARY-F-W"
        },
        {
            "type": "Feature",
            "domain": "1001574781348255SECONDARY-COMP",
            "range": "1001557342574188-SECONDARY-F-W"
        },
        {
            "type": "BetterThan",
            "domain": "1001557342574188-SECONDARY-F-W",
            "range": "1001552910237435-PRIMARY-F-W"
        },
        {
            "type": "Feature",
            "domain": "1506574774330-MAIN",
            "range": "1001592918667316-PRIMARY-F-W"
        },
        {
            "type": "Feature",
            "domain": "1001574781348255SECONDARY-COMP",
            "range": "1001601705360089-SECONDARY-F-W"
        },
        {
            "type": "BetterThan",
            "domain": "1001601705360089-SECONDARY-F-W",
            "range": "1001592918667316-PRIMARY-F-W"
        },
        {
            "type": "Feature",
            "domain": "1506574774330-MAIN",
            "range": "1001532324589255-PRIMARY-F-W"
        },
        {
            "type": "Feature",
            "domain": "1001574781348255SECONDARY-COMP",
            "range": "1001592383393787-SECONDARY-F-W"
        },
        {
            "type": "BetterThan",
            "domain": "1001592383393787-SECONDARY-F-W",
            "range": "1001532324589255-PRIMARY-F-W"
        },
        {
            "type": "Feature",
            "domain": "1506574774330-MAIN",
            "range": "1001526947455622-PRIMARY-F-W"
        },
        {
            "type": "Feature",
            "domain": "1001574781348255SECONDARY-COMP",
            "range": "1001580035854389-SECONDARY-F-W"
        },
        {
            "type": "BetterThan",
            "domain": "1001580035854389-SECONDARY-F-W",
            "range": "1001526947455622-PRIMARY-F-W"
        },
        {
            "type": "Feature",
            "domain": "1506574774330-MAIN",
            "range": "1001533638975049-PRIMARY-F-W"
        },
        {
            "type": "Feature",
            "domain": "1001574781348255SECONDARY-COMP",
            "range": "1001606277188894-SECONDARY-F-W"
        },
        {
            "type": "BetterThan",
            "domain": "1001606277188894-SECONDARY-F-W",
            "range": "1001533638975049-PRIMARY-F-W"
        },
        {
            "type": "Feature",
            "domain": "1506574774330-MAIN",
            "range": "1001546289795499-PRIMARY-F-B"
        },
        {
            "type": "Feature",
            "domain": "1001561567996095SECONDARY-COMP",
            "range": "1001593782684838-SECONDARY-F-B"
        },
        {
            "type": "BetterThan",
            "domain": "1001546289795499-PRIMARY-F-B",
            "range": "1001593782684838-SECONDARY-F-B"
        },
        {
            "type": "Feature",
            "domain": "1506574774330-MAIN",
            "range": "1001577933622736-PRIMARY-F-B"
        },
        {
            "type": "Feature",
            "domain": "1001561567996095SECONDARY-COMP",
            "range": "1001555246396621-SECONDARY-F-B"
        },
        {
            "type": "BetterThan",
            "domain": "1001577933622736-PRIMARY-F-B",
            "range": "1001555246396621-SECONDARY-F-B"
        },
        {
            "type": "Feature",
            "domain": "1506574774330-MAIN",
            "range": "1001578400534440-PRIMARY-F-B"
        },
        {
            "type": "Feature",
            "domain": "1001561567996095SECONDARY-COMP",
            "range": "1001519316407760-SECONDARY-F-B"
        },
        {
            "type": "BetterThan",
            "domain": "1001578400534440-PRIMARY-F-B",
            "range": "1001519316407760-SECONDARY-F-B"
        },
        {
            "type": "Feature",
            "domain": "1506574774330-MAIN",
            "range": "1001555300999784-PRIMARY-F-B"
        },
        {
            "type": "Feature",
            "domain": "1001561567996095SECONDARY-COMP",
            "range": "1001593049314830-SECONDARY-F-B"
        },
        {
            "type": "BetterThan",
            "domain": "1001555300999784-PRIMARY-F-B",
            "range": "1001593049314830-SECONDARY-F-B"
        },
        {
            "type": "Feature",
            "domain": "1506574774330-MAIN",
            "range": "1001555218634616-PRIMARY-F-B"
        },
        {
            "type": "Feature",
            "domain": "1001561567996095SECONDARY-COMP",
            "range": "1001519750688250-SECONDARY-F-B"
        },
        {
            "type": "BetterThan",
            "domain": "1001555218634616-PRIMARY-F-B",
            "range": "1001519750688250-SECONDARY-F-B"
        },
        {
            "type": "Feature",
            "domain": "1506574774330-MAIN",
            "range": "1001523255446042-PRIMARY-F-B"
        },
        {
            "type": "Feature",
            "domain": "1001561567996095SECONDARY-COMP",
            "range": "1001578735487700-SECONDARY-F-B"
        },
        {
            "type": "BetterThan",
            "domain": "1001523255446042-PRIMARY-F-B",
            "range": "1001578735487700-SECONDARY-F-B"
        },
        {
            "type": "Feature",
            "domain": "1506574774330-MAIN",
            "range": "1001536458264060-PRIMARY-F-B"
        },
        {
            "type": "Feature",
            "domain": "1001561567996095SECONDARY-COMP",
            "range": "1001524714473217-SECONDARY-F-B"
        },
        {
            "type": "BetterThan",
            "domain": "1001536458264060-PRIMARY-F-B",
            "range": "1001524714473217-SECONDARY-F-B"
        },
        {
            "type": "Feature",
            "domain": "1506574774330-MAIN",
            "range": "1001524014455570-PRIMARY-F-W"
        },
        {
            "type": "Feature",
            "domain": "1001561567996095SECONDARY-COMP",
            "range": "1001560981394422-SECONDARY-F-W"
        },
        {
            "type": "BetterThan",
            "domain": "1001560981394422-SECONDARY-F-W",
            "range": "1001524014455570-PRIMARY-F-W"
        },
        {
            "type": "Feature",
            "domain": "1506574774330-MAIN",
            "range": "1001580699194853-PRIMARY-F-B"
        },
        {
            "type": "Feature",
            "domain": "1001557491074504SECONDARY-COMP",
            "range": "1001596083444196-SECONDARY-F-B"
        },
        {
            "type": "BetterThan",
            "domain": "1001580699194853-PRIMARY-F-B",
            "range": "1001596083444196-SECONDARY-F-B"
        },
        {
            "type": "Feature",
            "domain": "1506574774330-MAIN",
            "range": "1001523637731584-PRIMARY-F-B"
        },
        {
            "type": "Feature",
            "domain": "1001557491074504SECONDARY-COMP",
            "range": "1001546049526848-SECONDARY-F-B"
        },
        {
            "type": "BetterThan",
            "domain": "1001523637731584-PRIMARY-F-B",
            "range": "1001546049526848-SECONDARY-F-B"
        },
        {
            "type": "Feature",
            "domain": "1506574774330-MAIN",
            "range": "101514611476312-PRIMARY-F-B"
        },
        {
            "type": "Feature",
            "domain": "1001557491074504SECONDARY-COMP",
            "range": "1001522472525948-SECONDARY-F-B"
        },
        {
            "type": "BetterThan",
            "domain": "101514611476312-PRIMARY-F-B",
            "range": "1001522472525948-SECONDARY-F-B"
        },
        {
            "type": "Feature",
            "domain": "1506574774330-MAIN",
            "range": "1001520432937542-PRIMARY-F-B"
        },
        {
            "type": "Feature",
            "domain": "1001557491074504SECONDARY-COMP",
            "range": "1001605545396267-SECONDARY-F-B"
        },
        {
            "type": "BetterThan",
            "domain": "1001520432937542-PRIMARY-F-B",
            "range": "1001605545396267-SECONDARY-F-B"
        },
        {
            "type": "Feature",
            "domain": "1506574774330-MAIN",
            "range": "1001599460652519-PRIMARY-F-B"
        },
        {
            "type": "Feature",
            "domain": "1001557491074504SECONDARY-COMP",
            "range": "1001562523286535-SECONDARY-F-B"
        },
        {
            "type": "BetterThan",
            "domain": "1001599460652519-PRIMARY-F-B",
            "range": "1001562523286535-SECONDARY-F-B"
        },
        {
            "type": "Feature",
            "domain": "1506574774330-MAIN",
            "range": "1001549274360064-PRIMARY-F-B"
        },
        {
            "type": "Feature",
            "domain": "1001557491074504SECONDARY-COMP",
            "range": "1001588540332929-SECONDARY-F-B"
        },
        {
            "type": "BetterThan",
            "domain": "1001549274360064-PRIMARY-F-B",
            "range": "1001588540332929-SECONDARY-F-B"
        },
        {
            "type": "Feature",
            "domain": "1506574774330-MAIN",
            "range": "1001552660575255-PRIMARY-F-B"
        },
        {
            "type": "Feature",
            "domain": "1001557491074504SECONDARY-COMP",
            "range": "1001536516873354-SECONDARY-F-B"
        },
        {
            "type": "BetterThan",
            "domain": "1001552660575255-PRIMARY-F-B",
            "range": "1001536516873354-SECONDARY-F-B"
        },
        {
            "type": "Feature",
            "domain": "1506574774330-MAIN",
            "range": "1001585621000735-PRIMARY-F-W"
        },
        {
            "type": "Feature",
            "domain": "1001557491074504SECONDARY-COMP",
            "range": "1001526240646677-SECONDARY-F-W"
        },
        {
            "type": "BetterThan",
            "domain": "1001526240646677-SECONDARY-F-W",
            "range": "1001585621000735-PRIMARY-F-W"
        },
        {
            "type": "Feature",
            "domain": "1506574774330-MAIN",
            "range": "101509713888169-PRIMARY-F-B"
        },
        {
            "type": "Feature",
            "domain": "1001529140722869SECONDARY-COMP",
            "range": "1001597984606635-SECONDARY-F-B"
        },
        {
            "type": "BetterThan",
            "domain": "101509713888169-PRIMARY-F-B",
            "range": "1001597984606635-SECONDARY-F-B"
        },
        {
            "type": "Feature",
            "domain": "1506574774330-MAIN",
            "range": "1001520545707248-PRIMARY-F-W"
        },
        {
            "type": "Feature",
            "domain": "1001529140722869SECONDARY-COMP",
            "range": "101515929053841-SECONDARY-F-W"
        },
        {
            "type": "BetterThan",
            "domain": "101515929053841-SECONDARY-F-W",
            "range": "1001520545707248-PRIMARY-F-W"
        },
        {
            "type": "Feature",
            "domain": "1506574774330-MAIN",
            "range": "1001538446826513-PRIMARY-F-W"
        },
        {
            "type": "Feature",
            "domain": "1001529140722869SECONDARY-COMP",
            "range": "1001546759981361-SECONDARY-F-W"
        },
        {
            "type": "BetterThan",
            "domain": "1001546759981361-SECONDARY-F-W",
            "range": "1001538446826513-PRIMARY-F-W"
        },
        {
            "type": "Feature",
            "domain": "1506574774330-MAIN",
            "range": "1001553461717210-PRIMARY-F-W"
        },
        {
            "type": "Feature",
            "domain": "1001529140722869SECONDARY-COMP",
            "range": "1001596316513351-SECONDARY-F-W"
        },
        {
            "type": "BetterThan",
            "domain": "1001596316513351-SECONDARY-F-W",
            "range": "1001553461717210-PRIMARY-F-W"
        },
        {
            "type": "Feature",
            "domain": "1506574774330-MAIN",
            "range": "1001527921388439-PRIMARY-F-W"
        },
        {
            "type": "Feature",
            "domain": "1001529140722869SECONDARY-COMP",
            "range": "1001539299734753-SECONDARY-F-W"
        },
        {
            "type": "BetterThan",
            "domain": "1001539299734753-SECONDARY-F-W",
            "range": "1001527921388439-PRIMARY-F-W"
        },
        {
            "type": "Feature",
            "domain": "1506574774330-MAIN",
            "range": "1001542998140097-PRIMARY-F-W"
        },
        {
            "type": "Feature",
            "domain": "1001529140722869SECONDARY-COMP",
            "range": "101512547987305-SECONDARY-F-W"
        },
        {
            "type": "BetterThan",
            "domain": "101512547987305-SECONDARY-F-W",
            "range": "1001542998140097-PRIMARY-F-W"
        },
        {
            "type": "Feature",
            "domain": "1506574774330-MAIN",
            "range": "1001580487252448-PRIMARY-F-W"
        },
        {
            "type": "Feature",
            "domain": "1001529140722869SECONDARY-COMP",
            "range": "1001574744280709-SECONDARY-F-W"
        },
        {
            "type": "BetterThan",
            "domain": "1001574744280709-SECONDARY-F-W",
            "range": "1001580487252448-PRIMARY-F-W"
        },
        {
            "type": "Feature",
            "domain": "1506574774330-MAIN",
            "range": "1001526465727367-PRIMARY-F-W"
        },
        {
            "type": "Feature",
            "domain": "1001529140722869SECONDARY-COMP",
            "range": "1001574439034590-SECONDARY-F-W"
        },
        {
            "type": "BetterThan",
            "domain": "1001574439034590-SECONDARY-F-W",
            "range": "1001526465727367-PRIMARY-F-W"
        },
        {
            "type": "Feature",
            "domain": "1506574774330-MAIN",
            "range": "1001523651161326-PRIMARY-F-W"
        },
        {
            "type": "Feature",
            "domain": "1001529140722869SECONDARY-COMP",
            "range": "1001546074453906-SECONDARY-F-W"
        },
        {
            "type": "BetterThan",
            "domain": "1001546074453906-SECONDARY-F-W",
            "range": "1001523651161326-PRIMARY-F-W"
        },
        {
            "type": "Feature",
            "domain": "1506574774330-MAIN",
            "range": "1001598563436141-PRIMARY-F-W"
        },
        {
            "type": "Feature",
            "domain": "1001529140722869SECONDARY-COMP",
            "range": "1001547463793705-SECONDARY-F-W"
        },
        {
            "type": "BetterThan",
            "domain": "1001547463793705-SECONDARY-F-W",
            "range": "1001598563436141-PRIMARY-F-W"
        },
        {
            "type": "Feature",
            "domain": "1506574774330-MAIN",
            "range": "1001593422606263-PRIMARY-F-B"
        },
        {
            "type": "Feature",
            "domain": "1001528841782316SECONDARY-COMP",
            "range": "1001538801159665-SECONDARY-F-B"
        },
        {
            "type": "BetterThan",
            "domain": "1001593422606263-PRIMARY-F-B",
            "range": "1001538801159665-SECONDARY-F-B"
        },
        {
            "type": "Feature",
            "domain": "1506574774330-MAIN",
            "range": "1001570897858755-PRIMARY-F-B"
        },
        {
            "type": "Feature",
            "domain": "1001528841782316SECONDARY-COMP",
            "range": "1001581873923938-SECONDARY-F-B"
        },
        {
            "type": "BetterThan",
            "domain": "1001570897858755-PRIMARY-F-B",
            "range": "1001581873923938-SECONDARY-F-B"
        },
        {
            "type": "Feature",
            "domain": "1506574774330-MAIN",
            "range": "1001605860927354-PRIMARY-F-B"
        },
        {
            "type": "Feature",
            "domain": "1001528841782316SECONDARY-COMP",
            "range": "1001564622639214-SECONDARY-F-B"
        },
        {
            "type": "BetterThan",
            "domain": "1001605860927354-PRIMARY-F-B",
            "range": "1001564622639214-SECONDARY-F-B"
        },
        {
            "type": "Feature",
            "domain": "1506574774330-MAIN",
            "range": "101510901576398-PRIMARY-F-B"
        },
        {
            "type": "Feature",
            "domain": "1001528841782316SECONDARY-COMP",
            "range": "1001598768302265-SECONDARY-F-B"
        },
        {
            "type": "BetterThan",
            "domain": "101510901576398-PRIMARY-F-B",
            "range": "1001598768302265-SECONDARY-F-B"
        },
        {
            "type": "Feature",
            "domain": "1506574774330-MAIN",
            "range": "1001560374860700-PRIMARY-F-B"
        },
        {
            "type": "Feature",
            "domain": "1001528841782316SECONDARY-COMP",
            "range": "101514926097450-SECONDARY-F-B"
        },
        {
            "type": "BetterThan",
            "domain": "1001560374860700-PRIMARY-F-B",
            "range": "101514926097450-SECONDARY-F-B"
        },
        {
            "type": "Feature",
            "domain": "1506574774330-MAIN",
            "range": "1001524158415502-PRIMARY-F-B"
        },
        {
            "type": "Feature",
            "domain": "1001528841782316SECONDARY-COMP",
            "range": "1001569659327322-SECONDARY-F-B"
        },
        {
            "type": "BetterThan",
            "domain": "1001524158415502-PRIMARY-F-B",
            "range": "1001569659327322-SECONDARY-F-B"
        },
        {
            "type": "Feature",
            "domain": "1506574774330-MAIN",
            "range": "1001587742218936-PRIMARY-F-B"
        },
        {
            "type": "Feature",
            "domain": "1001528841782316SECONDARY-COMP",
            "range": "1001557888228075-SECONDARY-F-B"
        },
        {
            "type": "BetterThan",
            "domain": "1001587742218936-PRIMARY-F-B",
            "range": "1001557888228075-SECONDARY-F-B"
        },
        {
            "type": "Feature",
            "domain": "1506574774330-MAIN",
            "range": "1001519359510510-PRIMARY-F-W"
        },
        {
            "type": "Feature",
            "domain": "1001528841782316SECONDARY-COMP",
            "range": "1001603904945778-SECONDARY-F-W"
        },
        {
            "type": "BetterThan",
            "domain": "1001603904945778-SECONDARY-F-W",
            "range": "1001519359510510-PRIMARY-F-W"
        },
        {
            "type": "Feature",
            "domain": "1506574774330-MAIN",
            "range": "1001588774473036-PRIMARY-F-B"
        },
        {
            "type": "Feature",
            "domain": "1001527086380312SECONDARY-COMP",
            "range": "1001525483679354-SECONDARY-F-B"
        },
        {
            "type": "BetterThan",
            "domain": "1001588774473036-PRIMARY-F-B",
            "range": "1001525483679354-SECONDARY-F-B"
        },
        {
            "type": "Feature",
            "domain": "1506574774330-MAIN",
            "range": "1001517235659041-PRIMARY-F-B"
        },
        {
            "type": "Feature",
            "domain": "1001527086380312SECONDARY-COMP",
            "range": "1001586349124324-SECONDARY-F-B"
        },
        {
            "type": "BetterThan",
            "domain": "1001517235659041-PRIMARY-F-B",
            "range": "1001586349124324-SECONDARY-F-B"
        },
        {
            "type": "Feature",
            "domain": "1506574774330-MAIN",
            "range": "1001547812924699-PRIMARY-F-B"
        },
        {
            "type": "Feature",
            "domain": "1001527086380312SECONDARY-COMP",
            "range": "1001588709825163-SECONDARY-F-B"
        },
        {
            "type": "BetterThan",
            "domain": "1001547812924699-PRIMARY-F-B",
            "range": "1001588709825163-SECONDARY-F-B"
        },
        {
            "type": "Feature",
            "domain": "1506574774330-MAIN",
            "range": "1001571422615020-PRIMARY-F-W"
        },
        {
            "type": "Feature",
            "domain": "1001527086380312SECONDARY-COMP",
            "range": "1001561163044187-SECONDARY-F-W"
        },
        {
            "type": "BetterThan",
            "domain": "1001561163044187-SECONDARY-F-W",
            "range": "1001571422615020-PRIMARY-F-W"
        },
        {
            "type": "Feature",
            "domain": "1506574774330-MAIN",
            "range": "1001533644329898-PRIMARY-F-B"
        },
        {
            "type": "Feature",
            "domain": "1001529764561007SECONDARY-COMP",
            "range": "1001579811505300-SECONDARY-F-B"
        },
        {
            "type": "BetterThan",
            "domain": "1001533644329898-PRIMARY-F-B",
            "range": "1001579811505300-SECONDARY-F-B"
        },
        {
            "type": "Feature",
            "domain": "1506574774330-MAIN",
            "range": "101514333070373-PRIMARY-F-B"
        },
        {
            "type": "Feature",
            "domain": "1001529764561007SECONDARY-COMP",
            "range": "1001569369115310-SECONDARY-F-B"
        },
        {
            "type": "BetterThan",
            "domain": "101514333070373-PRIMARY-F-B",
            "range": "1001569369115310-SECONDARY-F-B"
        },
        {
            "type": "Feature",
            "domain": "1506574774330-MAIN",
            "range": "1001521288655630-PRIMARY-F-B"
        },
        {
            "type": "Feature",
            "domain": "1001529764561007SECONDARY-COMP",
            "range": "1001540416688497-SECONDARY-F-B"
        },
        {
            "type": "BetterThan",
            "domain": "1001521288655630-PRIMARY-F-B",
            "range": "1001540416688497-SECONDARY-F-B"
        },
        {
            "type": "Feature",
            "domain": "1506574774330-MAIN",
            "range": "101515462077457-PRIMARY-F-B"
        },
        {
            "type": "Feature",
            "domain": "1001529764561007SECONDARY-COMP",
            "range": "101515554831271-SECONDARY-F-B"
        },
        {
            "type": "BetterThan",
            "domain": "101515462077457-PRIMARY-F-B",
            "range": "101515554831271-SECONDARY-F-B"
        },
        {
            "type": "Feature",
            "domain": "1506574774330-MAIN",
            "range": "1001552741628468-PRIMARY-F-B"
        },
        {
            "type": "Feature",
            "domain": "1001529764561007SECONDARY-COMP",
            "range": "1001551769720951-SECONDARY-F-B"
        },
        {
            "type": "BetterThan",
            "domain": "1001552741628468-PRIMARY-F-B",
            "range": "1001551769720951-SECONDARY-F-B"
        },
        {
            "type": "Feature",
            "domain": "1506574774330-MAIN",
            "range": "1001541005418731-PRIMARY-F-W"
        },
        {
            "type": "Feature",
            "domain": "1001529764561007SECONDARY-COMP",
            "range": "1001596224367178-SECONDARY-F-W"
        },
        {
            "type": "BetterThan",
            "domain": "1001596224367178-SECONDARY-F-W",
            "range": "1001541005418731-PRIMARY-F-W"
        }
    ]
}